vbhelloworld/__init__.py
vbhelloworld-1.0.3.1.data/data/etc/helloworld.conf
vbhelloworld-1.0.3.1.dist-info/METADATA
vbhelloworld-1.0.3.1.dist-info/RECORD
vbhelloworld-1.0.3.1.dist-info/WHEEL
vbhelloworld-1.0.3.1.dist-info/entry_points.txt
vbhelloworld-1.0.3.1.dist-info/top_level.txt
